README.md
setup.py
reproxy/__init__.py
reproxy/async_requests.py
reproxy.egg-info/PKG-INFO
reproxy.egg-info/SOURCES.txt
reproxy.egg-info/dependency_links.txt
reproxy.egg-info/requires.txt
reproxy.egg-info/top_level.txt