Metadata-Version: 2.1
Name: reproxy
Version: 1.0.0
Summary: proxy request pass by redis
Home-page: 
Author: aidenmo
Author-email: aidenmo@tencent.com
Keywords: proxy,requests
Classifier: Programming Language :: Python :: 3 :: Only
Classifier: Programming Language :: Python :: 3.6
Classifier: Programming Language :: Python :: 3.7
Classifier: Programming Language :: Python :: 3.8
Classifier: Programming Language :: Python :: 3.9
Classifier: License :: OSI Approved :: MIT License
Classifier: Operating System :: OS Independent
